orrery/__init__.py
orrery/models.py
orrery/observable.py
orrery-0.1.1.dist-info/METADATA
orrery-0.1.1.dist-info/WHEEL
orrery-0.1.1.dist-info/licenses/LICENSE
orrery-0.1.1.dist-info/RECORD
