Metadata-Version: 2.4
Name: orrery
Version: 0.1.1
Summary: A framework for supporting MVC and observer patterns in Python
Project-URL: Documentation, https://github.com/CodeChoreography/orrery#readme
Project-URL: Issues, https://github.com/CodeChoreography/orrery/issues
Project-URL: Source, https://github.com/CodeChoreography/orrery
Author-email: Tom Doel <tom.doel@codechoreography.co.uk>
License-Expression: MIT
License-File: LICENSE
Classifier: Development Status :: 4 - Beta
Classifier: Programming Language :: Python
Classifier: Programming Language :: Python :: 3.9
Classifier: Programming Language :: Python :: 3.10
Classifier: Programming Language :: Python :: 3.11
Classifier: Programming Language :: Python :: 3.12
Classifier: Programming Language :: Python :: Implementation :: CPython
Classifier: Programming Language :: Python :: Implementation :: PyPy
Requires-Python: >=3.9
Provides-Extra: docs
Requires-Dist: myst-parser; extra == 'docs'
Requires-Dist: pydata-sphinx-theme; extra == 'docs'
Requires-Dist: sphinx; extra == 'docs'
Requires-Dist: sphinx-autodoc-typehints; extra == 'docs'
Provides-Extra: lint
Requires-Dist: pylint; extra == 'lint'
Provides-Extra: tests
Requires-Dist: pytest; extra == 'tests'
